Workbook

Sheet 00_Sommaire
A1: DOSSIER 1 - CONTRÔLE DE GESTION INDUSTRIEL (MÉCANO-EST SAS)
A3: Onglet | B3: Objet de la modélisation | C3: Méthodes & Outils mobilisés | D3: Enseignement clé / Décision
A4: 01_Methode_ABC | B4: Comptabilité par activités (ABC) vs Méthode classique | C4: Inducteurs de coûts, subventionnement croisé | D4: Mise en évidence du déficit de la gamme spéciale (-41,50 €/u) masqué par le standard.
A5: 02_Valorisation_Stocks | B5: Suivi des stocks d'acier : FIFO (PEPS) vs PUMP | C5: Fiche de stock mensuelle, impact inflation | D5: Le FIFO majore le résultat (+157 €) en période de hausse des prix face au PUMP.
A6: 03_Seuil_Rentabilite | B6: Analyse coût-volume-profit & levier opérationnel | C6: Compte de résultat différentiel, point mort | D6: Seuil de rentabilité à 677 k€ (277 jours), marge de sécurité à 23,1 %.

Sheet 01_Methode_ABC
A1: DOSSIER 1 - PME MÉCANO-EST SAS : COMPTABILITÉ PAR ACTIVITÉS (ABC)
A3: 1. Données d'activité et charges directes
A4: Paramètres de production & Vente | B4: Standard (S) | C4: Spéciale (P) | D4: Total Entreprise
A5: Volume annuel produit et vendu (unités) | B5: 10000 | C5: 2000 | D5: =B5+C5 -> 12000
A6: Prix de vente unitaire (€) | B6: 60 | C6: 140
A7: Chiffre d'affaires global (€) | B7: =B5*B6 -> 600000 | C7: =C5*C6 -> 280000 | D7: =B7+C7 -> 880000
A8: Matières premières directes (€/u) | B8: 15 | C8: 35
A9: Heures de MOD par unité (h/u) | B9: 0.5 | C9: 1.2
A10: Taux horaire de la MOD (€/h) | B10: 30 | C10: 30
A11: Total heures MOD consommées (h) | B11: =B5*B9 -> 5000 | C11: =C5*C9 -> 2400 | D11: =B11+C11 -> 7400
A12: Total charges directes unitaires (€/u) | B12: =B8+(B9*B10) -> 30 | C12: =C8+(C9*C10) -> 71
A14: 2. Cartographie des activités et coûts des inducteurs
A15: Activité support | B15: Inducteur retenu | C15: Vol. (S) | D15: Vol. (P) | E15: Total Inducteurs | F15: Coût Activité (€) | G15: Coût unitaire Inducteur (€)
A16: Approvisionnement | B16: Nombre de commandes | C16: 40 | D16: 80 | E16: =C16+D16 -> 120 | F16: 60000 | G16: =F16/E16 -> 500
A17: Réglage machines | B17: Nombre de séries lancées | C17: 20 | D17: 80 | E17: =C17+D17 -> 100 | F17: 80000 | G17: =F17/E17 -> 800
A18: Usinage | B18: Heures-machines | C18: 5000 | D18: 3000 | E18: =C18+D18 -> 8000 | F18: 120000 | G18: =F18/E18 -> 15
A19: Contrôle qualité | B19: Nombre de lots contrôlés | C19: 20 | D19: 80 | E19: =C19+D19 -> 100 | F19: 60000 | G19: =F19/E19 -> 600
A20: Expédition / ADV | B20: Nombre de livraisons | C20: 80 | D20: 120 | E20: =C20+D20 -> 200 | F20: 40000 | G20: =F20/E20 -> 200
A21: TOTAL CHARGES INDIRECTES | B21: - | C21: N/A | D21: N/A | E21: N/A | F21: =SUM(F16:F20) -> 360000 | G21: N/A
A23: 3. Comparaison : Méthode Traditionnelle vs Méthode ABC
A24: Méthode de calcul | B24: Indicateur unitaire | C24: Standard (S) | D24: Spéciale (P) | E24: Total Société
A25: Méthode classique (Clé = h MOD) | B25: Charges directes unitaires | C25: =B12 -> 30 | D25: =C12 -> 71 | E25: -
B26: Charges indirectes unitaires | C26: =(F21*(B11/$D$11))/B5 -> 24.324324 | D26: =(F21*(C11/$D$11))/C5 -> 58.378378 | E26: =F21 -> 360000
B27: Coût de revient unitaire | C27: =C25+C26 -> 54.324324 | D27: =D25+D26 -> 129.37838 | E27: -
B28: Prix de vente unitaire | C28: =B6 -> 60 | D28: =C6 -> 140 | E28: -
B29: Marge unitaire (€) | C29: =C28-C27 -> 5.6756757 | D29: =D28-D27 -> 10.621622 | E29: =D7-(C25*B5+D25*C5)-F21 -> 78000
B30: Taux de marge (%) | C30: =C29/C28 -> 0.094594595 | D30: =D29/D28 -> 0.075868726 | E30: =E29/D7 -> 0.088636364
A31: Méthode ABC (Inducteurs d'activité) | B31: Charges directes unitaires | C31: =B12 -> 30 | D31: =C12 -> 71 | E31: -
B32: Charges indirectes unitaires | C32: =SUMPRODUCT(C16:C20,$G16:$G20)/B5 -> 13.9 | D32: =SUMPRODUCT(D16:D20,$G16:$G20)/C5 -> 110.5 | E32: =F21 -> 360000
B33: Coût de revient unitaire | C33: =C31+C32 -> 43.9 | D33: =D31+D32 -> 181.5 | E33: -
B34: Prix de vente unitaire | C34: =B6 -> 60 | D34: =C6 -> 140 | E34: -
B35: Marge unitaire (€) | C35: =C34-C33 -> 16.1 | D35: =D34-D33 -> -41.5 | E35: =D7-(C31*B5+D31*C5)-F21 -> 78000
B36: Taux de marge (%) | C36: =C35/C34 -> 0.26833333 | D36: =D35/D34 -> -0.29642857 | E36: =E35/D7 -> 0.088636364

Sheet 02_Valorisation_Stocks
A1: DOSSIER 1 (SUITE) - GESTION ET VALORISATION DES STOCKS : FIFO vs PUMP
A3: 1. Fiche de stock chronologique (Acier haute résistance)
A4: Date | B4: Opération | C4: Quantité (kg) | D4: P.U. (€) | E4: Montant (€) | F4: Stock Q (kg) | G4: Stock FIFO (€) | H4: Stock PUMP (€) | I4: PUMP (€/kg)
A5: 01/01 | B5: Stock initial | C5: 200 | D5: 10 | E5: =C5*D5 -> 2000 | F5: =C5 -> 200 | G5: =E5 -> 2000 | H5: =E5 -> 2000 | I5: =H5/F5 -> 10
A6: 08/01 | B6: Entrée (E1) | C6: 300 | D6: 12 | E6: =C6*D6 -> 3600 | F6: =F5+C6 -> 500 | G6: =G5+E6 -> 5600 | H6: =H5+E6 -> 5600 | I6: =H6/F6 -> 11.2
A7: 15/01 | B7: Sortie atelier (S1) | C7: -350 | F7: =F6+C7 -> 150 | G7: =G6-(MIN(C5,-C7)*D5+MAX(-C7-C5,0)*D6) -> 1800 | H7: =H6+C7*I6 -> 1680 | I7: =H7/F7 -> 11.2
A8: 22/01 | B8: Entrée (E2) | C8: 400 | D8: 13.5 | E8: =C8*D8 -> 5400 | F8: =F7+C8 -> 550 | G8: =G7+E8 -> 7200 | H8: =H7+E8 -> 7080 | I8: =H8/F8 -> 12.872727
A9: 28/01 | B9: Sortie atelier (S2) | C9: -300 | F9: =F8+C9 -> 250 | G9: =G8-(MIN(C6-MAX(-C7-C5,0),-C9)*D6+MAX(-C9-(C6-MAX(-C7-C5,0)),0)*D8) -> 3375 | H9: =H8+C9*I8 -> 3218.1818 | I9: =H9/F9 -> 12.872727
A12: 2. Synthèse d'impact financier : FIFO vs PUMP
A13: Agrégat financier | B13: Méthode FIFO | C13: Méthode PUMP | D13: Écart (FIFO - PUMP) | E13: Impact sur les états financiers
A14: Coût des matières consommées (Sorties) | B14: =(G6-G7)+(G8-G9) -> 7625 | C14: =(H6-H7)+(H8-H9) -> 7781.8182 | D14: =B14-C14 -> -156.81818 | E14: Charges minorées en FIFO -> Majore le résultat d'exploitation
A15: Valeur du stock final (Bilan au 31/01) | B15: =G9 -> 3375 | C15: =H9 -> 3218.1818 | D15: =B15-C15 -> 156.81818 | E15: Actif circulant valorisé au plus près des prix récents du marché
A16: Total disponible réconcilié (Sorties + SF) | B16: =B14+B15 -> 11000 | C16: =C14+C15 -> 11000 | D16: =B16-C16 -> 0 | E16: Contrôle d'inventaire parfait (écart de bouclage nul)

Sheet 03_Seuil_Rentabilite
A1: DOSSIER 1 (SUITE) - SEUIL DE RENTABILITÉ ET RISQUE D'EXPLOITATION
A3: 1. Compte de résultat différentiel
A4: Poste de gestion | B4: Montant (€) | C4: % du Chiffre d'affaires | D4: Nature de variabilité
A5: Chiffre d'affaires (CA) | B5: ='01_Methode_ABC'!D7 -> 880000 | C5: =B5/$B$5 -> 1 | D5: Volume d'activité annuel
A6: Matières premières directes | B6: =SUMPRODUCT('01_Methode_ABC'!B8:C8,'01_Methode_ABC'!B5:C5) -> 220000 | C6: =B6/$B$5 -> 0.25 | D6: 100 % variable
A7: Main-d'œuvre directe (MOD) | B7: ='01_Methode_ABC'!D11*'01_Methode_ABC'!B10 -> 222000 | C7: =B7/$B$5 -> 0.25227273 | D7: Considérée variable à la production
A8: Énergie et outillage variable | B8: ='01_Methode_ABC'!F18*0.5 -> 60000 | C8: =B8/$B$5 -> 0.068181818 | D8: Part variable usinage (50 %)
A9: Frais d'expédition / transport | B9: ='01_Methode_ABC'!F20 -> 40000 | C9: =B9/$B$5 -> 0.045454545 | D9: 100 % variable
A10: TOTAL CHARGES VARIABLES (CV) | B10: =SUM(B6:B9) -> 542000 | C10: =B10/$B$5 -> 0.61590909 | D10: Proportionnel à l'activité
A11: MARGE SUR COÛTS VARIABLES (MCV) | B11: =B5-B10 -> 338000 | C11: =B11/$B$5 -> 0.38409091 | D11: Contribution à la couverture des frais fixes
A12: TOTAL CHARGES FIXES (CF) | B12: ='01_Methode_ABC'!F16+'01_Methode_ABC'!F17+'01_Methode_ABC'!F19+'01_Methode_ABC'!F18*0.5 -> 260000 | C12: =B12/$B$5 -> 0.29545455 | D12: Appro, réglages, contrôle, amortissements
A13: RÉSULTAT D'EXPLOITATION | B13: =B11-B12 -> 78000 | C13: =B13/$B$5 -> 0.088636364 | D13: Bénéfice opérationnel net
A16: 2. Indicateurs de sécurité financière et de sensibilité
A17: Indicateur de risque | B17: Formule de calcul | C17: Valeur calculée | D17: Interprétation pour le management
A18: Seuil de rentabilité (SR en €) | B18: Charges fixes / Taux de MCV | C18: =B12/C11 -> 676923.08 | D18: Niveau de CA à atteindre pour couvrir l'intégralité des charges
A19: Point mort (base annuelle 360 jours) | B19: (SR / CA) * 360 jours | C19: =(C18/B5)*360 -> 276.92308 | D19: L'activité devient profitable à compter du 8 octobre
A20: Marge de sécurité (€) | B20: CA - SR | C20: =B5-C18 -> 203076.92 | D20: Baisse de chiffre d'affaires absorbable avant d'entrer en perte
A21: Indice de sécurité (%) | B21: Marge de sécurité / CA | C21: =C20/B5 -> 0.23076923 | D21: Le CA peut fléchir de 23,1 % sans générer de perte
A22: Levier d'exploitation | B22: MCV / Résultat d'exploitation | C22: =B11/B13 -> 4.3333333 | D22: Une hausse de 10 % de l'activité entraîne +43,3 % de résultat
